setup.py
commis/__init__.py
commis/scripts/__init__.py
commis/scripts/commis.py
commis/scripts/ingredient_category.py
commis/scripts/offical_ingredients/__init__.py
commis/scripts/offical_ingredients/basic_image_processing.py
commis/tests/__init__.py
commis/tests/test_commis.py
commis/tests/test_official_ingredients.py
ngon_commis.egg-info/PKG-INFO
ngon_commis.egg-info/SOURCES.txt
ngon_commis.egg-info/dependency_links.txt
ngon_commis.egg-info/requires.txt
ngon_commis.egg-info/top_level.txt